fuzzy_dates/__init__.py
fuzzy_dates/__main__.py
fuzzy_dates/engine.py
fuzzy_dates/grammar.pl
fuzzy_dates/facts/french.pl
fuzzy_dates/facts/german.pl
fuzzy_dates/facts/swedish.pl
fuzzy_dates-0.2.19.dist-info/LICENSE
fuzzy_dates-0.2.19.dist-info/METADATA
fuzzy_dates-0.2.19.dist-info/WHEEL
fuzzy_dates-0.2.19.dist-info/entry_points.txt
fuzzy_dates-0.2.19.dist-info/top_level.txt
fuzzy_dates-0.2.19.dist-info/RECORD
