Metadata-Version: 2.1
Name: fuzzy-dates
Version: 0.2.19
Summary: A parser for fuzzy dates
Home-page: https://github.com/openengines/fuzzy_dates
Author: Real Python
Author-email: openengines@protonmail.com
License: MIT
Platform: UNKNOWN
Classifier: License :: OSI Approved :: MIT License
Classifier: Programming Language :: Python :: 3
Classifier: Programming Language :: Python :: 3.7
Requires-Dist: pyswip
Requires-Dist: pytest
